shillelagh_gristapi/__init__.py
shillelagh_gristapi/adapter.py
shillelagh_gristapi/cache.py
shillelagh_gristapi/http.py
shillelagh_gristapi/schema.py
shillelagh_gristapi-0.1.7.dist-info/licenses/LICENSE
shillelagh_gristapi-0.1.7.dist-info/METADATA
shillelagh_gristapi-0.1.7.dist-info/WHEEL
shillelagh_gristapi-0.1.7.dist-info/entry_points.txt
shillelagh_gristapi-0.1.7.dist-info/top_level.txt
shillelagh_gristapi-0.1.7.dist-info/RECORD
