Metadata-Version: 2.4
Name: shillelagh-gristapi
Version: 0.1.7
Summary: Shillelagh adapter to query Grist documents and tables via SQL.
Author: Quentin Leroy
License: MIT License
Project-URL: Homepage, https://github.com/qleroy/shillelagh-gristapi
Project-URL: Issues, https://github.com/qleroy/shillelagh-gristapi/issues
Keywords: shillelagh,grist,sql,adapter,superset
Requires-Python: >=3.9
License-File: LICENSE
Requires-Dist: shillelagh>=1.4.0
Requires-Dist: requests<3,>=2.32.0
Provides-Extra: dev
Requires-Dist: pytest>=8.2; extra == "dev"
Requires-Dist: pytest-cov>=5.0; extra == "dev"
Requires-Dist: responses>=0.25.0; extra == "dev"
Requires-Dist: ruff>=0.6.9; extra == "dev"
Requires-Dist: mypy>=1.11.2; extra == "dev"
Requires-Dist: types-requests; extra == "dev"
Requires-Dist: build; extra == "dev"
Dynamic: license-file
